{
  "name": "ForestCrossroad4Execution",
  "width": 7200,
  "height": 7200,
  "grid": 150,
  "shiftX": 0,
  "shiftY": 0,
  "gridDistance": 5.0,
  "gridUnits": "ft",
  "padding": 0.0,
  "gridColor": "#000000",
  "gridAlpha": 0.2,
  "globalLight": true,
  "darkness": 0.6,
  "lights": [
    {
      "x": 2876,
      "y": 3058,
      "dim": 20.0,
      "bright": 10.0,
      "tintColor": "#FFAD40",
      "tintAlpha": 0.13
    },
    {
      "x": 4039,
      "y": 4522,
      "dim": 20.0,
      "bright": 10.0,
      "tintColor": "#FFAD40",
      "tintAlpha": 0.13
    },
    {
      "x": 4267,
      "y": 2995,
      "dim": 37.5,
      "bright": 18.75,
      "tintColor": "#FF9A00",
      "tintAlpha": 0.13
    },
    {
      "x": 5548,
      "y": 3764,
      "dim": 20.0,
      "bright": 10.0,
      "tintColor": "#FFAD40",
      "tintAlpha": 0.13
    }
  ],
  "walls": [],
  "img": null,
  "foreground": null
}